superagentx_examples/README.md
superagentx_examples/__init__.py
superagentx_examples/coffeecompass/CoffeeCompass.png
superagentx_examples/coffeecompass/README.md
superagentx_examples/coffeecompass/coffeecompass/__init__.py
superagentx_examples/coffeecompass/coffeecompass/config.py
superagentx_examples/coffeecompass/coffeecompass/handler/coffeecompass_handler.py
superagentx_examples/coffeecompass/coffeecompass/iopipe.py
superagentx_examples/coffeecompass/coffeecompass/pipe.py
superagentx_examples/coffeecompass/coffeecompass/restpipe.py
superagentx_examples/coffeecompass/coffeecompass/wspipe.py
superagentx_examples/coffeecompass/output_json.png
superagentx_examples/coffeecompass/poetry.lock
superagentx_examples/coffeecompass/pyproject.toml
superagentx_examples/coffeecompass/screens.png
superagentx_examples/doctor appointment/README.md
superagentx_examples/doctor appointment/doctor_appointment/__init__.py
superagentx_examples/doctor appointment/doctor_appointment/config.py
superagentx_examples/doctor appointment/doctor_appointment/data/hospital_data.sqlite3
superagentx_examples/doctor appointment/doctor_appointment/data/images/SuperAgentX-Doctor-Appointment-Booking-App.png
superagentx_examples/doctor appointment/doctor_appointment/data/images/doctor_app_architecture.png
superagentx_examples/doctor appointment/doctor_appointment/iopipe.py
superagentx_examples/doctor appointment/doctor_appointment/pipe.py
superagentx_examples/doctor appointment/doctor_appointment/restpipe.py
superagentx_examples/doctor appointment/doctor_appointment/wspipe.py
superagentx_examples/doctor appointment/poetry.lock
superagentx_examples/doctor appointment/pyproject.toml
superagentx_examples/ecom/README.md
superagentx_examples/ecom/ecom/__init__.py
superagentx_examples/ecom/ecom/config.py
superagentx_examples/ecom/ecom/iopipe.py
superagentx_examples/ecom/ecom/pipe.py
superagentx_examples/ecom/ecom/restpipe.py
superagentx_examples/ecom/ecom/wspipe.py
superagentx_examples/ecom/poetry.lock
superagentx_examples-0.1.3.1.dist-info/LICENSE
superagentx_examples-0.1.3.1.dist-info/METADATA
superagentx_examples-0.1.3.1.dist-info/WHEEL
superagentx_examples-0.1.3.1.dist-info/RECORD
