Metadata-Version: 2.3
Name: superagentx-examples
Version: 0.1.3.1
Summary: 
Keywords: superagentX,AGI,Agentic AI,ASI,superagentx,superagentx-examples,agent,LLM
Author: SuperAgentX AI
Author-email: support@superagentx.ai
Maintainer: SuperAgentX AI
Maintainer-email: support@superagentx.ai
Requires-Python: >=3.10,<=3.13
Classifier: Programming Language :: Python :: 3
Classifier: Programming Language :: Python :: 3.10
Classifier: Programming Language :: Python :: 3.11
Classifier: Programming Language :: Python :: 3.12
Classifier: Programming Language :: Python :: 3.13
Requires-Dist: fastapi[standard] (>=0.115.4,<0.116.0)
Requires-Dist: rich (>=13.9.2,<14.0.0)
Requires-Dist: superagentx (>=0.1.12,<0.2.0)
Requires-Dist: superagentx-handlers (>=0.1.5,<0.2.0)
Requires-Dist: websockets (>=13.1,<14.0)
Project-URL: Documentation, https://docs.superagentx.ai/
Project-URL: Homepage, https://www.superagentx.ai/
Project-URL: Repository, https://github.com/superagentxai/superagentx-examples
